Ld/__init__.py
Ld/bot.py
Ld/client.py
Ld/defaults.py
Ld/deviceauths.py
Ld/sync.py
Ld/web.py
ledxbot-2.5.8.dist-info/METADATA
ledxbot-2.5.8.dist-info/WHEEL
ledxbot-2.5.8.dist-info/top_level.txt
ledxbot-2.5.8.dist-info/RECORD
