Metadata-Version: 2.1
Name: ledxbot
Version: 2.5.8
Summary: a advanced bot for fortnite
Home-page: UNKNOWN
Author: Led (HarryD)
Author-email: <ledxbotofficial@outlook.com>
License: UNKNOWN
Keywords: python,sanic,BenBotAsync,FortniteAPIAsync
Platform: UNKNOWN
Classifier: Development Status :: 1 - Planning
Classifier: Intended Audience :: Developers
Classifier: Programming Language :: Python :: 3
Classifier: Operating System :: Unix
Classifier: Operating System :: MacOS :: MacOS X
Classifier: Operating System :: Microsoft :: Windows
Requires-Dist: aiofiles
Requires-Dist: aiohttp
Requires-Dist: fortnitepy
Requires-Dist: sanic
Requires-Dist: BenBotAsync
Requires-Dist: FortniteAPIAsync
Requires-Dist: crayons
